"iva_package/Alex, VGG, ResNet, Parallel CNN EX3.py"
iva_package/Generative Adversarial Network and its features EX7.py
iva_package/Image translation GAN EX6.py
iva_package/MNIST using Keras EX2.py
iva_package/MNIST using TF Ex1.py
iva_package/Object Detection using CNN EX4.py
iva_package/Video Classification EX8.py
iva_package/Yolo EX5.py
iva_package/__init__.py
iva_package-0.1.1.dist-info/METADATA
iva_package-0.1.1.dist-info/WHEEL
iva_package-0.1.1.dist-info/top_level.txt
iva_package-0.1.1.dist-info/RECORD
