Metadata-Version: 2.1
Name: iva-package
Version: 0.1.1
Summary: 8 Python files
Home-page: UNKNOWN
Author: Unknown
License: UNKNOWN
Platform: UNKNOWN
Requires-Python: >=3.9
